uniserializer/__init__.py
uniserializer/deserializer.py
uniserializer/serializer.py
uniserializer-1.27.0.dist-info/LICENSE
uniserializer-1.27.0.dist-info/METADATA
uniserializer-1.27.0.dist-info/WHEEL
uniserializer-1.27.0.dist-info/top_level.txt
uniserializer-1.27.0.dist-info/RECORD
