Metadata-Version: 2.1
Name: uniserializer
Version: 1.27.0
Summary: Fast and efficient universal data serializer
Home-page: https://github.com/Diffylab/UniSerializer
Author: Diffy
Author-email: diffylab@gmail.com
License: MIT
Download-URL: https://github.com/Diffylab/UniSerializer/releases/
Keywords: Serializer,Deserializer,data,binary,encoding,schema, schemaless
Platform: UNKNOWN
Classifier: Programming Language :: Python :: 3
Classifier: License :: OSI Approved :: MIT License
Classifier: Topic :: Software Development :: Libraries
Classifier: Development Status :: 5 - Production/Stable
Classifier: Intended Audience :: Developers
Classifier: Intended Audience :: Science/Research
Classifier: Natural Language :: English
Classifier: Operating System :: OS Independent
Classifier: Topic :: Software Development :: Libraries :: Python Modules
